Workbook

Sheet Resumo
B2: Orçamento preliminar — Rádio Enlace UFERSA
B3: Pau dos Ferros ↔ Repetidora ↔ Apodi | Data-base 29/09/2026
B5: #gid=1142211786&range=B2
B6: #gid=1978796414&range=B2
B7: #gid=1184084880&range=B2
B9: Estimativa consolidada
B10: Componente | C10: Mínimo | D10: Base recomendada | E10: Alto
B11: Materiais | C11: =Materiais!K20 -> 73035.55 | D11: =Materiais!L20 -> 98782.55 | E11: =Materiais!M20 -> 149889.05
B12: Serviços, frete e contingência | C12: =Servicos!I10 -> 28146.764 | D12: =Servicos!J10 -> 48794.336 | E12: =Servicos!K10 -> 93189.219
B13: TOTAL DO PROJETO | C13: =C11+C12 -> 101182.31 | D13: =D11+D12 -> 147576.89 | E13: =E11+E12 -> 243078.27
B16: Correções técnicas incorporadas
B17: • 4 rádios e 4 antenas, pois a repetidora atende dois enlaces independentes e precisa de um conjunto por direção.
B18: • PoE 24 V/1 A e antena GPS já acompanham cada AF-5XHD; foram retirados como compras separadas.
B19: • Os jumpers RF e os suportes principais acompanham a antena/rádio; confirmar com o fornecedor antes da emissão do pedido.
B20: • Foram previstos 8 protetores ETH-SP-G2, seguindo a recomendação de dois por rádio.
B21: • O TOUGHCable/UISP Cable Carrier é Cat5e, não Cat6; foi orçada uma caixa de 305 m para cobrir 150 m de uso e reserva.
B24: Exclusões e alertas
B25: • Não inclui sistema de energia da repetidora (rede elétrica, solar, baterias, controlador, abrigo e climatização). Sem energia disponível no cume, esse subsistema pode ser relevante.
B26: • Não inclui aquisição/locação de terrenos, licenças, acesso viário, segurança patrimonial, impostos específicos ou mensalidades.
B27: • A fundação 1,5 x 1,5 x 1,5 m é apenas premissa acadêmica. Precisa de sondagem, cálculo estrutural, cargas de vento e ART.
B28: • Preços online variam com estoque, frete para o RN, ICMS/ST, forma de pagamento e validade da proposta. Obter ao menos três cotações formais.

Sheet Materiais
B2: Orçamento de materiais — enlace Pau dos Ferros ↔ Repetidora ↔ Apodi
B3: Data-base: 29/09/2026 | Valores em reais | Cenários mínimo, base e alto
B5: Categoria | C5: Modelo / descrição | D5: Qtd. informada | E5: Qtd. técnica | F5: Qtd. compra | G5: Unidade | H5: Preço mín. | I5: Preço base | J5: Preço alto | K5: Total mín. | L5: Total base | M5: Total alto | N5: Fonte / critério | O5: Tratamento | P5: Observação
B6: Rádio | C6: Ubiquiti airFiber 5XHD (AF-5XHD-BR) | D6: 3 | E6: 4 | F6: 4 | G6: peça | H6: 3595.56 | I6: 4749 | J6: 5759.99 | K6: =F6*H6 -> 14382.24 | L6: =F6*I6 -> 18996 | M6: =F6*J6 -> 23039.96 | N6: F01/F02/F03 | O6: Comprar | P6: Dois enlaces independentes exigem 4 rádios: A, 2 na repetidora e B.
B7: Antena | C7: Ubiquiti AF-5G30-S45, 30 dBi | D7: 3 | E7: 4 | F7: 4 | G7: peça | H7: 1303.55 | I7: 1957.34 | J7: 2500 | K7: =F7*H7 -> 5214.2 | L7: =F7*I7 -> 7829.36 | M7: =F7*J7 -> 10000 | N7: F04/F05 | O7: Comprar | P7: Uma antena por rádio; total de 4.
B8: Alimentação | C8: PoE Gigabit 24 V/1 A, modelo POE-24V-5X-HD | D8: 3 | E8: 4 | F8: 0 | G8: peça | H8: 0 | I8: 0 | J8: 0 | K8: =F8*H8 -> 0 | L8: =F8*I8 -> 0 | M8: =F8*J8 -> 0 | N8: F06 | O8: Incluso | P8: O adaptador correto acompanha cada AF-5XHD; não comprar INS-3G-24V separadamente.
B9: Sincronismo | C9: Antena GPS externa com base magnética | D9: 1 | E9: 4 | F9: 0 | G9: peça | H9: 0 | I9: 0 | J9: 0 | K9: =F9*H9 -> 0 | L9: =F9*I9 -> 0 | M9: =F9*J9 -> 0 | N9: F06 | O9: Incluso | P9: A antena GPS acompanha cada rádio.
B10: Cabeamento | C10: UISP Cable Carrier/TOUGHCable Carrier, caixa 305 m, Cat5e blindado outdoor | D10: 110 | E10: 150 | F10: 1 | G10: caixa 305 m | H10: 2289.5 | I10: 2289.5 | J10: 2543.89 | K10: =F10*H10 -> 2289.5 | L10: =F10*I10 -> 2289.5 | M10: =F10*J10 -> 2543.89 | N10: F07 | O10: Comprar | P10: 110 m tende a ser insuficiente para 4 descidas; reserva técnica adotada: 150 m. O produto Ubiquiti é Cat5e, não Cat6.
B11: Conectividade | C11: TOUGHConnector TC-GND, caixa com 20 | D11: 6 | E11: 8 | F11: 1 | G11: caixa 20 | H11: 145.99 | I11: 145.99 | J11: 561.4 | K11: =F11*H11 -> 145.99 | L11: =F11*I11 -> 145.99 | M11: =F11*J11 -> 561.4 | N11: F08 | O11: Comprar | P11: São necessários ao menos 8 conectores para 4 descidas; a embalagem cobre sobressalentes.
B12: RF | C12: Jumpers/pigtails RF resistentes ao tempo | D12: 6 | E12: 8 | F12: 0 | G12: peça | H12: 0 | I12: 0 | J12: 0 | K12: =F12*H12 -> 0 | L12: =F12*I12 -> 0 | M12: =F12*J12 -> 0 | N12: F09 | O12: Incluso | P12: A AF-5G30-S45 inclui jumpers RF; confirmar conteúdo na compra.
B13: Proteção | C13: Ubiquiti ETH-SP-G2 | D13: 3 | E13: 8 | F13: 8 | G13: peça | H13: 96.74 | I13: 99 | J13: 127.35 | K13: =F13*H13 -> 773.92 | L13: =F13*I13 -> 792 | M13: =F13*J13 -> 1018.8 | N13: F10/F11 | O13: Comprar | P13: A Ubiquiti recomenda dois protetores por rádio: próximo ao equipamento e na entrada da instalação.
B14: Fixação | C14: airFiber X mount, suporte da antena e ferragens principais | D14: 3 | E14: 4 | F14: 0 | G14: kit | H14: 0 | I14: 0 | J14: 0 | K14: =F14*H14 -> 0 | L14: =F14*I14 -> 0 | M14: =F14*J14 -> 0 | N14: F06/F09 | O14: Incluso | P14: Suportes principais acompanham rádio/antena.
B15: Fixação | C15: Ferragens complementares, prensa-cabos, abraçadeiras UV e eletrodutos | D15: 0 | E15: 3 | F15: 3 | G15: kit/site | H15: 200 | I15: 300 | J15: 500 | K15: =F15*H15 -> 600 | L15: =F15*I15 -> 900 | M15: =F15*J15 -> 1500 | N15: P01 | O15: Provisão | P15: Provisão editável; confirmar após vistoria.
B16: Estrutura | C16: Torre estaiada galvanizada de 30 m, nova, com cabos | D16: 3 | E16: 3 | F16: 3 | G16: peça | H16: 11000 | I16: 15290 | J16: 27075 | K16: =F16*H16 -> 33000 | L16: =F16*I16 -> 45870 | M16: =F16*J16 -> 81225 | N16: F12/F13 | O16: Comprar/cotar | P16: Exige projeto estrutural, cargas de vento, galvanização, ART e definição do terreno.
B17: Obra civil | C17: Fundação completa preliminar 1,5 x 1,5 x 1,5 m | D17: 3 | E17: 3 | F17: 3 | G17: unidade | H17: 4500 | I17: 6000 | J17: 8000 | K17: =F17*H17 -> 13500 | L17: =F17*I17 -> 18000 | M17: =F17*J17 -> 24000 | N17: F14/P02 | O17: Provisão | P17: Inclui provisão de escavação, concreto, aço, fôrma e execução. Dimensão deve ser validada por engenheiro e sondagem.
... B19: Rede repetidora | C19: Switch Gigabit gerenciável para interligar os 2 rádios da repetidora | D19: 0 | E19: 1 | F19: 1 | G19: peça | H19: 700 | I19: 900 | J19: 1500 | K19: =F19*H19 -> 700 | L19: =F19*I19 -> 900 | M19: =F19*J19 -> 1500 | N19: P03 | O19: Provisão | P19: Modelo e alimentação dependem da infraestrutura elétrica/solar do cume.
B20: TOTAL DE MATERIAIS | K20: =SUM(K6:K19) -> 73035.55 | L20: =SUM(L6:L19) -> 98782.55 | M20: =SUM(M6:M19) -> 149889.05

Sheet Servicos
B2: Serviços, logística e reservas
B3: Premissas editáveis em azul; totais calculados por fórmulas
B5: Item | C5: Critério | D5: Qtd. | E5: Unidade | F5: Custo mín. | G5: Custo base | H5: Custo alto | I5: Total mín. | J5: Total base | K5: Total alto | L5: Fonte / critério
B6: Montagem das torres, lançamento de cabos, instalação e alinhamento | C6: Provisão por site; exigir equipe NR-10/NR-35 e responsável técnico | D6: 3 | E6: site | F6: 4000 | G6: 6000 | H6: 9000 | I6: =D6*F6 -> 12000 | J6: =D6*G6 -> 18000 | K6: =D6*H6 -> 27000 | L6: P04
B7: Projeto executivo, memorial, ART e comissionamento | C7: Provisão global; escopo final a cotar | D7: 1 | E7: lote | F7: 5000 | G7: 7500 | H7: 12000 | I7: =D7*F7 -> 5000 | J7: =D7*G7 -> 7500 | K7: =D7*H7 -> 12000 | L7: P05
B8: Frete e logística | C8: Percentual sobre materiais | D8: 1 | E8: percentual | F8: 0.05 | G8: 0.1 | H8: 0.15 | I8: =Materiais!K20*F8 -> 3651.7775 | J8: =Materiais!L20*G8 -> 9878.255 | K8: =Materiais!M20*H8 -> 22483.357 | L8: P06
B9: Reserva de contingência | C9: Percentual sobre materiais + serviços + frete | D9: 1 | E9: percentual | F9: 0.08 | G9: 0.1 | H9: 0.15 | I9: =(Materiais!K20+SUM(I6:I8))*F9 -> 7494.9862 | J9: =(Materiais!L20+SUM(J6:J8))*G9 -> 13416.081 | K9: =(Materiais!M20+SUM(K6:K8))*H9 -> 31705.861 | L9: P07
B10: TOTAL SERVIÇOS, FRETE E RESERVA | I10: =SUM(I6:I9) -> 28146.764 | J10: =SUM(J6:J9) -> 48794.336 | K10: =SUM(K6:K9) -> 93189.219

Sheet Fontes e Premissas
B2: Fontes de preços e premissas
B3: Preços consultados em 29/09/2026; hyperlinks clicáveis
B5: Código | C5: Item | D5: Preço/critério observado | E5: Fonte | F5: URL | G5: Uso no orçamento | H5: Observação
B6: F01 | C6: AF-5XHD | D6: R$ 3.595,56 à vista | E6: NR Store | F6: https://www.nrstore.com.br/www-nrstore-com-br/ubiquiti-af-5xhd-airfiber-radio-ip-67-5ghz-1gbps | G6: Preço mínimo | H6: Anúncio informa PoE incluso.
B7: F02 | C7: AF-5XHD | D7: R$ 4.749,00 à vista | E7: KaBuM | F7: https://www.kabum.com.br/produto/356910/radio-ubiquiti-airfiber-5x-hd-5ghz-1gb-200-km-gps-af-5xhd-br-ubiquiti- | G7: Preço base | H7: Referência intermediária.
B8: F03 | C8: AF-5XHD | D8: R$ 5.759,99 | E8: Magazine Luiza | F8: https://www.magazineluiza.com.br/radio-ubiquiti-airfiber-5ghz-1gbps-gps-branco-af-5xhd/p/aj41cgha9j/ea/rapo/ | G8: Preço alto | H8: Marketplace; conferir vendedor.
B9: F04 | C9: AF-5G30-S45 | D9: R$ 1.303,55 à vista | E9: Tudo em Ubiquiti | F9: https://www.tudoemubiquiti.com.br/t/categoria-tudo-em-ubiquiti/airfiber/antenas | G9: Preço mínimo | H9: Consulta online.
B10: F05 | C10: AF-5G30-S45 | D10: R$ 1.957,34 a R$ 2.500,00 | E10: TRT16 / pesquisa de preços | F10: https://www.trt16.jus.br/site/conteudo/contas/arq_extrato_inexigibilidade_dispensa.php?idn=38631&atributo=PESQUISA_PRECO | G10: Base e alto | H10: Pesquisa pública com duas referências.
B11: F06 | C11: Conteúdo AF-5XHD | D11: PoE 24 V/1 A, GPS, suporte e kit IP67 inclusos | E11: Ubiquiti | F11: https://dl.ui.com/guides/airfiber/airFiber_AF-5XHD_QSG.pdf | G11: Evita duplicidade | H11: Fabricante determina uso do adaptador incluído POE-24V-5X-HD.
B12: F07 | C12: UISP Cable Carrier 305 m | D12: R$ 2.289,50 à vista; R$ 2.543,89 parcelado | E12: Net Computadores | F12: https://netcomputadores.com.br/p/uispcablecarrier-ubiquiti-cabo-de-rede/105657 | G12: Mínimo/base/alto | H12: Produto é Cat5e blindado 24 AWG, não Cat6.
B13: F08 | C13: TC-GND, caixa 20 | D13: R$ 145,99 a R$ 28,07/unidade | E13: Biostech / MyGigaTech | F13: https://www.biostechconecta.com.br/ubiquiti-tc-gnd-toughcable-cabo-de-conector-rj45-caixa-com-20-pecas | G13: Preço conectores | H13: Confirmar estoque e embalagem.
B14: F09 | C14: Conteúdo AF-5G30-S45 | D14: Suporte universal, suporte do rádio e jumpers RF inclusos | E14: Ubiquiti | F14: https://dl.ui.com/qsg/AF-5G30-S45/AF-5G30-S45_EN.html | G14: Evita duplicidade | H14: Conteúdo oficial da antena.
B15: F10 | C15: ETH-SP-G2 | D15: R$ 99,00 | E15: Ubiquiti Brasil | F15: https://br.store.ui.com/br/pt/products/ethernet-surge-protector | G15: Preço base | H15: Preço com imposto informado na loja.
B16: F11 | C16: ETH-SP-G2 | D16: R$ 96,74 a R$ 127,35 | E16: NR Store / Tudo em Ubiquiti | F16: https://www.nrstore.com.br/www-nrstore-com-br/ubiquiti-eth-sp-g2-ethernet-surge-protector-gen-2 | G16: Faixa de preço | H16: A Ubiquiti recomenda dois protetores por enlace outdoor/radio.
... B20: F15 | C20: Kit para-raio 30 m | D20: R$ 1.019,90 | E20: Magazine Luiza | F20: https://www.magazineluiza.com.br/busca/haste+de+aterramento+cobre/ | G20: Preço base | H20: Referência comercial; não substitui projeto de SPDA.
B21: P01 | C21: Ferragens complementares | D21: R$ 200 a R$ 500/site | E21: Premissa editável | G21: Provisão | H21: Confirmar após vistoria.
B22: P02 | C22: Fundação completa | D22: R$ 4.500 a R$ 8.000/site | E22: Premissa editável | G22: Provisão | H22: Faixa preliminar; não é proposta de empreiteira.
B23: P03 | C23: Switch da repetidora | D23: R$ 700 a R$ 1.500 | E23: Premissa editável | G23: Provisão | H23: Selecionar conforme energia e gerenciamento.
B24: P04 | C24: Instalação e alinhamento | D24: R$ 4.000 a R$ 9.000/site | E24: Premissa editável | G24: Provisão | H24: Exigir NR-10, NR-35, seguro e ART.
B25: P05 | C25: Projeto/ART/comissionamento | D25: R$ 5.000 a R$ 12.000/lote | E25: Premissa editável | G25: Provisão | H25: Escopo depende de sondagem e projeto estrutural.
B26: P06 | C26: Frete/logística | D26: 5% / 10% / 15% dos materiais | E26: Premissa editável | G26: Provisão | H26: Frete de torres pode alterar substancialmente o custo.
B27: P07 | C27: Contingência | D27: 8% / 10% / 15% | E27: Premissa editável | G27: Provisão | H27: Aplicada após materiais, serviços e frete.
